odoo/addons/mail_activity_meeting_reminder/README.rst
odoo/addons/mail_activity_meeting_reminder/__init__.py
odoo/addons/mail_activity_meeting_reminder/__manifest__.py
odoo/addons/mail_activity_meeting_reminder/i18n/it.po
odoo/addons/mail_activity_meeting_reminder/i18n/mail_activity_meeting_reminder.pot
odoo/addons/mail_activity_meeting_reminder/models/__init__.py
odoo/addons/mail_activity_meeting_reminder/models/mail_activity.py
odoo/addons/mail_activity_meeting_reminder/models/mail_activity_type.py
odoo/addons/mail_activity_meeting_reminder/readme/CONTRIBUTORS.md
odoo/addons/mail_activity_meeting_reminder/readme/DESCRIPTION.md
odoo/addons/mail_activity_meeting_reminder/static/description/icon.png
odoo/addons/mail_activity_meeting_reminder/static/description/index.html
odoo/addons/mail_activity_meeting_reminder/views/mail_activity_type.xml
odoo_addon_mail_activity_meeting_reminder-16.0.1.0.0.4.dist-info/METADATA
odoo_addon_mail_activity_meeting_reminder-16.0.1.0.0.4.dist-info/WHEEL
odoo_addon_mail_activity_meeting_reminder-16.0.1.0.0.4.dist-info/top_level.txt
odoo_addon_mail_activity_meeting_reminder-16.0.1.0.0.4.dist-info/RECORD
